odoo9_addon_website_sale_checkout_country_vat-9.0.1.1.0-py2.7-nspkg.pth
odoo9_addon_website_sale_checkout_country_vat-9.0.1.1.0.dist-info/DESCRIPTION.rst
odoo9_addon_website_sale_checkout_country_vat-9.0.1.1.0.dist-info/METADATA
odoo9_addon_website_sale_checkout_country_vat-9.0.1.1.0.dist-info/RECORD
odoo9_addon_website_sale_checkout_country_vat-9.0.1.1.0.dist-info/WHEEL
odoo9_addon_website_sale_checkout_country_vat-9.0.1.1.0.dist-info/metadata.json
odoo9_addon_website_sale_checkout_country_vat-9.0.1.1.0.dist-info/namespace_packages.txt
odoo9_addon_website_sale_checkout_country_vat-9.0.1.1.0.dist-info/top_level.txt
odoo_addons/website_sale_checkout_country_vat/README.rst
odoo_addons/website_sale_checkout_country_vat/__init__.py
odoo_addons/website_sale_checkout_country_vat/__openerp__.py
odoo_addons/website_sale_checkout_country_vat/i18n/es.po
odoo_addons/website_sale_checkout_country_vat/static/description/icon.png
odoo_addons/website_sale_checkout_country_vat/static/src/js/change_country.js
odoo_addons/website_sale_checkout_country_vat/views/assets.xml
odoo_addons/website_sale_checkout_country_vat/views/templates.xml
